<?xml version="1.0" encoding="UTF-8"?>
<!DOCTYPE mapper PUBLIC "-//mybatis.org//DTD Mapper 3.0//EN" "http://mybatis.org/dtd/mybatis-3-mapper.dtd">
<mapper namespace="elabuelonicolas.bd.mappers.ListacompraMapper">
	<resultMap id="BaseResultMap"
		type="elabuelonicolas.bd.domain.Listacompra">
		<!-- WARNING - @mbg.generated This element is automatically generated by 
			MyBatis Generator, do not modify. This element was generated on Thu May 31 
			22:35:26 CDT 2018. -->
		<id column="id" jdbcType="INTEGER" property="id" />
		<result column="idcompra" jdbcType="INTEGER"
			property="idcompra" />
		<result column="idproducto" jdbcType="INTEGER"
			property="idproducto" />
		<result column="cantidad" jdbcType="INTEGER"
			property="cantidad" />
		<result column="subtotal" jdbcType="DOUBLE" property="subtotal" />
	</resultMap>
	<select id="findAll" resultMap="BaseResultMap">
		SELECT * FROM listacompra
	</select>
	<insert id="create"
		parameterType="elabuelonicolas.bd.domain.Listacompra">
		insert into listacompra (id,idproducto, idcompra,
		cantidad, subtotal)
		values (#{id},#{idproducto}, #{idcompra},
		#{cantidad}, #{subtotal})
	</insert>
	<select id="read" parameterType="int" resultMap="BaseResultMap">
		select * from
		listacompra where id=#{id}
	</select>
	<update id="update"
		parameterType="elabuelonicolas.bd.domain.Listacompra">
		UPDATE listacompra SET
		id=#{id},
		idproducto=#{idproducto},
		idcompra=#{idcompra},
		cantidad=#{cantidad},
		subtotal=#{subtotal}
		WHERE id=#{id}
	</update>
	<delete id="delete" parameterType="int">
		delete from listacompra where
		id =
		#{id}
	</delete>

</mapper>